uteis/__init__.py
uteis/catex.py
uteis/ficheiro.py
uteis/imprimir.py
uteis-0.1.2.2.dist-info/LICENSE
uteis-0.1.2.2.dist-info/METADATA
uteis-0.1.2.2.dist-info/WHEEL
uteis-0.1.2.2.dist-info/top_level.txt
uteis-0.1.2.2.dist-info/RECORD
