Metadata-Version: 2.1
Name: uteis
Version: 0.1.2.2
Summary: Paquetes con funcións uteis para programar en python
Home-page: https://wwww.github.com/Ran-n/uteis
Author: Ran#
Author-email: ran-n@tutanota.com
License: GPLv3
Project-URL: Bug Tracker, https://wwww.github.com/Ran-n/uteis/issues
Platform: UNKNOWN
Classifier: Development Status :: 1 - Planning
Classifier: Environment :: Console
Classifier: Intended Audience :: Developers
Classifier: License :: OSI Approved :: GNU General Public License v3 (GPLv3)
Classifier: Operating System :: OS Independent
Classifier: Programming Language :: Python :: 3.8
Classifier: Topic :: Software Development :: Libraries
Classifier: Topic :: Text Processing :: General
Classifier: Natural Language :: Galician
Classifier: Natural Language :: Portuguese
Classifier: Natural Language :: English
Classifier: Natural Language :: Spanish
Requires-Python: >=3.8.5
License-File: LICENSE
